financial_metrix_by_podpivas/__init__.py
financial_metrix_by_podpivas/calculator.py
financial_metrix_by_podpivas/main.py
financial_metrix_by_podpivas-0.1.dist-info/METADATA
financial_metrix_by_podpivas-0.1.dist-info/WHEEL
financial_metrix_by_podpivas-0.1.dist-info/entry_points.txt
financial_metrix_by_podpivas-0.1.dist-info/top_level.txt
financial_metrix_by_podpivas-0.1.dist-info/RECORD
