Metadata-Version: 2.1
Name: financial_metrix_by_podpivas
Version: 0.1
Summary: A package for calculating net profit and ROI
Author: podpivas
Author-email: k.shaykhraziev@edu.centraluniversity.ru
Requires-Dist: setuptools
